{
    "keep": {
        "days": true,
        "amount": 15
    },
    "auditLog": "D:\\New folder\\privateProject\\backend\\printx\\.f7c23348ad6cbfcacd3709e5ea1f1a789e868fd7-audit.json",
    "files": [
        {
            "date": 1722707273190,
            "name": "D:\\New folder\\privateProject\\backend\\printx\\printx-2024-08-03.log",
            "hash": "0e0faa64d673286ba0319f89b2c4da1e5db2e097f19f67743b004a92dbd343da"
        },
        {
            "date": 1722781387992,
            "name": "D:\\New folder\\privateProject\\backend\\printx\\printx-2024-08-04.log",
            "hash": "b50237043ee2b1898acee6ea5ab915dda24162aadfacf1f75f3c3efcbc830877"
        },
        {
            "date": 1722841786026,
            "name": "D:\\New folder\\privateProject\\backend\\printx\\printx-2024-08-05.log",
            "hash": "66a51b96c028b9be6887db31df98013eb99fff1fc40931b5e7d662d3974f28c1"
        },
        {
            "date": 1722964071766,
            "name": "D:\\New folder\\privateProject\\backend\\printx\\printx-2024-08-06.log",
            "hash": "65742f9a2b2100bad0fbee418567741a1debd85caffc8f55cd26d46754537759"
        },
        {
            "date": 1723014578438,
            "name": "D:\\New folder\\privateProject\\backend\\printx\\printx-2024-08-07.log",
            "hash": "d7e99fb597eb6b57ea9e1150f049190ad5d9cba0531cead23e51a76543028e80"
        },
        {
            "date": 1723108026141,
            "name": "D:\\New folder\\privateProject\\backend\\printx\\printx-2024-08-08.log",
            "hash": "37c67f5ece6f7299a6bbcab9e63e0eabb8df378e9e5cf09e70942b43e6b44a48"
        },
        {
            "date": 1723186811182,
            "name": "D:\\New folder\\privateProject\\backend\\printx\\printx-2024-08-09.log",
            "hash": "79d8b525f3635d7151ed66b06fad5a9ae54e51e85c0db708df0863ab218c1649"
        },
        {
            "date": 1723300190545,
            "name": "D:\\New folder\\privateProject\\backend\\printx\\printx-2024-08-10.log",
            "hash": "abff9bb728c439c52065be7c798553dd7eb411118f664ee825bf8ebf6e4f6634"
        },
        {
            "date": 1723362000283,
            "name": "D:\\New folder\\privateProject\\backend\\printx\\printx-2024-08-11.log",
            "hash": "5e4b7e7f820b270bbce2acde08e49a4df20746bf5db596586e2169304603ef2c"
        },
        {
            "date": 1723537355634,
            "name": "D:\\New folder\\privateProject\\backend\\printx\\printx-2024-08-13.log",
            "hash": "7e423816fd6b1f5b4abd112b699e76f98fe7510fd5321aff55342b4c3aeb97ab"
        },
        {
            "date": 1723701442768,
            "name": "D:\\New folder\\privateProject\\backend\\printx\\printx-2024-08-14.log",
            "hash": "11b09d86c01fd312ac379fc5423700accae9f08884782e23452c9d4fe57cc82c"
        },
        {
            "date": 1723705213555,
            "name": "D:\\New folder\\privateProject\\backend\\printx\\printx-2024-08-15.log",
            "hash": "08dc9e25de9affe4ce74ad38e8de9d2c5d451e7c2aec7d5cac0acf33a0cc3022"
        },
        {
            "date": 1723881300382,
            "name": "D:\\New folder\\privateProject\\backend\\printx\\printx-2024-08-17.log",
            "hash": "bac1caf4df72c827bf8bbefecc62d6c99e23620758fc07d7f11756e0334ace61"
        }
    ],
    "hashType": "sha256"
}